shift_register/shift_register.v
module shift_register (clk, reset, in, out);
	input wire clk, reset;
	input wire [4:0] in;
	output [3:0] out;

  parameter SIZE = 64;
	integer i;

  reg [SIZE-1:0] ser;

	initial begin
		ser = 0;
	end

	always@(posedge clk)
	begin

		if(reset == 1'b1) begin
			ser = 0;
		end
		else begin
	    for(i=0 ; i<5 ; i=i+1) begin
				ser[SIZE-1:1] = ser[SIZE-2:0];
				ser[0] = in[4-i];
	    end
		end
		// $display("%b",ser);
	end

	assign out = ser[SIZE-1:SIZE-4];
endmodule

shift_register/testbench/shift_register_tb.v
`include "../shift_register.v"

module test;
    reg [4:0] in;
    reg clk;
    reg reset;
    wire [3:0] out;

    shift_register #(8) shRe (clk, reset, in, out);

    initial
    begin
    $monitor("in: %b, clock: %b, reset: %b, out: %b --- at time %t", in, clk, reset, out, $time);
    $dumpfile("shift_register.vcd");
    $dumpvars(0,test);

        in = 5'b10110;
        #1
        in = 5'b10110;
        #1
        in = 5'b10110;
        #1
        in = 5'b10110;
        #1
        in = 5'b10110;
        #1
        in = 5'b10110;
        #1
        in = 5'b10110;
        #1
        in = 5'b10110;
        #1
        in = 5'b10110;
        #1
        in = 5'b10110;
        #1
        in = 5'b10110;
        #1
        in = 5'b10110;
        #1
        in = 5'b10110;
        #1
        in = 5'b10000;
        #1
        in = 5'b11010;
        #1
        in = 5'b00010;
        #1

        $finish;
    end

    integer i;
    initial begin
      clk = 0;
      forever begin
        #1
        clk = ~clk;
      end
    end

endmodule

shift_register/testbench/shift_register.vcd
$date
	Tue Jan 05 00:08:02 2021
$end
$version
	Icarus Verilog
$end
$timescale
	1s
$end
$scope module test $end
$var wire 4 ! out [3:0] $end
$var reg 1 " clk $end
$var reg 5 # in [4:0] $end
$var reg 1 $ reset $end
$scope module shRe $end
$var wire 1 " clk $end
$var wire 5 % in [4:0] $end
$var wire 1 $ reset $end
$var wire 4 & out [3:0] $end
$var reg 8 ' ser [7:0] $end
$var integer 32 ( i [31:0] $end
$upscope $end
$upscope $end
$enddefinitions $end
#0
$dumpvars
bx (
b0 '
b0 &
b10110 %
x$
b10110 #
0"
b0 !
$end
#1
b1 !
b1 &
b10110 '
b101 (
1"
#2
0"
#3
b1101 !
b1101 &
b11010110 '
b101 (
1"
#4
0"
#5
b11010110 '
b101 (
1"
#6
0"
#7
b11010110 '
b101 (
1"
#8
0"
#9
b11010110 '
b101 (
1"
#10
0"
#11
b11010110 '
b101 (
1"
#12
0"
#13
b11010000 '
b101 (
1"
b10000 #
b10000 %
#14
0"
b11010 #
b11010 %
#15
b0 !
b0 &
b10 '
b101 (
1"
b10 #
b10 %
